[
  {
    "id": "",
    "name_en": "Unknown Exercise",
    "name_ar": "Unknown (AR)",
    "description_en": "A cardio exercise focusing on the muscles.",
    "description_ar": "تمرين cardio يركز على muscles.",
    "category": "CARDIO",
    "primary_muscle": "CARDIO",
    "secondary_muscles": [],
    "equipment": [
      "BODYWEIGHT"
    ],
    "difficulty": "BEGINNER",
    "instructions_en": [
      "Step 1: Assume starting position.",
      "Step 2: Perform the movement.",
      "Step 3: Return to start."
    ],
    "instructions_ar": [
      "الخطوة ١: اتخذ وضعية البداية.",
      "الخطوة ٢: قم بأداء الحركة.",
      "الخطوة ٣: عد إلى وضعية البداية."
    ],
    "tips_en": [],
    "tips_ar": [],
    "is_time_based": false,
    "default_sets": 3,
    "default_reps": 12,
    "default_duration": null,
    "default_rest": 60,
    "tags": [
      "cardio",
      "bodyweight"
    ]
  },
  {
    "id": "",
    "name_en": "Unknown Exercise",
    "name_ar": "Unknown (AR)",
    "description_en": "A cardio exercise focusing on the muscles.",
    "description_ar": "تمرين cardio يركز على muscles.",
    "category": "CARDIO",
    "primary_muscle": "CARDIO",
    "secondary_muscles": [],
    "equipment": [
      "BODYWEIGHT"
    ],
    "difficulty": "BEGINNER",
    "instructions_en": [
      "Step 1: Assume starting position.",
      "Step 2: Perform the movement.",
      "Step 3: Return to start."
    ],
    "instructions_ar": [
      "الخطوة ١: اتخذ وضعية البداية.",
      "الخطوة ٢: قم بأداء الحركة.",
      "الخطوة ٣: عد إلى وضعية البداية."
    ],
    "tips_en": [],
    "tips_ar": [],
    "is_time_based": false,
    "default_sets": 3,
    "default_reps": 12,
    "default_duration": null,
    "default_rest": 60,
    "tags": [
      "cardio",
      "bodyweight"
    ]
  },
  {
    "id": "",
    "name_en": "Unknown Exercise",
    "name_ar": "Unknown (AR)",
    "description_en": "A cardio exercise focusing on the muscles.",
    "description_ar": "تمرين cardio يركز على muscles.",
    "category": "CARDIO",
    "primary_muscle": "CARDIO",
    "secondary_muscles": [],
    "equipment": [
      "BODYWEIGHT"
    ],
    "difficulty": "BEGINNER",
    "instructions_en": [
      "Step 1: Assume starting position.",
      "Step 2: Perform the movement.",
      "Step 3: Return to start."
    ],
    "instructions_ar": [
      "الخطوة ١: اتخذ وضعية البداية.",
      "الخطوة ٢: قم بأداء الحركة.",
      "الخطوة ٣: عد إلى وضعية البداية."
    ],
    "tips_en": [],
    "tips_ar": [],
    "is_time_based": false,
    "default_sets": 3,
    "default_reps": 12,
    "default_duration": null,
    "default_rest": 60,
    "tags": [
      "cardio",
      "bodyweight"
    ]
  },
  {
    "id": "",
    "name_en": "Unknown Exercise",
    "name_ar": "Unknown (AR)",
    "description_en": "A cardio exercise focusing on the muscles.",
    "description_ar": "تمرين cardio يركز على muscles.",
    "category": "CARDIO",
    "primary_muscle": "CARDIO",
    "secondary_muscles": [],
    "equipment": [
      "BODYWEIGHT"
    ],
    "difficulty": "BEGINNER",
    "instructions_en": [
      "Step 1: Assume starting position.",
      "Step 2: Perform the movement.",
      "Step 3: Return to start."
    ],
    "instructions_ar": [
      "الخطوة ١: اتخذ وضعية البداية.",
      "الخطوة ٢: قم بأداء الحركة.",
      "الخطوة ٣: عد إلى وضعية البداية."
    ],
    "tips_en": [],
    "tips_ar": [],
    "is_time_based": false,
    "default_sets": 3,
    "default_reps": 12,
    "default_duration": null,
    "default_rest": 60,
    "tags": [
      "cardio",
      "bodyweight"
    ]
  },
  {
    "id": "",
    "name_en": "Unknown Exercise",
    "name_ar": "Unknown (AR)",
    "description_en": "A cardio exercise focusing on the muscles.",
    "description_ar": "تمرين cardio يركز على muscles.",
    "category": "CARDIO",
    "primary_muscle": "CARDIO",
    "secondary_muscles": [],
    "equipment": [
      "BODYWEIGHT"
    ],
    "difficulty": "BEGINNER",
    "instructions_en": [
      "Step 1: Assume starting position.",
      "Step 2: Perform the movement.",
      "Step 3: Return to start."
    ],
    "instructions_ar": [
      "الخطوة ١: اتخذ وضعية البداية.",
      "الخطوة ٢: قم بأداء الحركة.",
      "الخطوة ٣: عد إلى وضعية البداية."
    ],
    "tips_en": [],
    "tips_ar": [],
    "is_time_based": false,
    "default_sets": 3,
    "default_reps": 12,
    "default_duration": null,
    "default_rest": 60,
    "tags": [
      "cardio",
      "bodyweight"
    ]
  },
  {
    "id": "",
    "name_en": "Unknown Exercise",
    "name_ar": "Unknown (AR)",
    "description_en": "A cardio exercise focusing on the muscles.",
    "description_ar": "تمرين cardio يركز على muscles.",
    "category": "CARDIO",
    "primary_muscle": "CARDIO",
    "secondary_muscles": [],
    "equipment": [
      "BODYWEIGHT"
    ],
    "difficulty": "BEGINNER",
    "instructions_en": [
      "Step 1: Assume starting position.",
      "Step 2: Perform the movement.",
      "Step 3: Return to start."
    ],
    "instructions_ar": [
      "الخطوة ١: اتخذ وضعية البداية.",
      "الخطوة ٢: قم بأداء الحركة.",
      "الخطوة ٣: عد إلى وضعية البداية."
    ],
    "tips_en": [],
    "tips_ar": [],
    "is_time_based": false,
    "default_sets": 3,
    "default_reps": 12,
    "default_duration": null,
    "default_rest": 60,
    "tags": [
      "cardio",
      "bodyweight"
    ]
  },
  {
    "id": "",
    "name_en": "Unknown Exercise",
    "name_ar": "Unknown (AR)",
    "description_en": "A cardio exercise focusing on the muscles.",
    "description_ar": "تمرين cardio يركز على muscles.",
    "category": "CARDIO",
    "primary_muscle": "CARDIO",
    "secondary_muscles": [],
    "equipment": [
      "BODYWEIGHT"
    ],
    "difficulty": "BEGINNER",
    "instructions_en": [
      "Step 1: Assume starting position.",
      "Step 2: Perform the movement.",
      "Step 3: Return to start."
    ],
    "instructions_ar": [
      "الخطوة ١: اتخذ وضعية البداية.",
      "الخطوة ٢: قم بأداء الحركة.",
      "الخطوة ٣: عد إلى وضعية البداية."
    ],
    "tips_en": [],
    "tips_ar": [],
    "is_time_based": false,
    "default_sets": 3,
    "default_reps": 12,
    "default_duration": null,
    "default_rest": 60,
    "tags": [
      "cardio",
      "bodyweight"
    ]
  },
  {
    "id": "",
    "name_en": "Unknown Exercise",
    "name_ar": "Unknown (AR)",
    "description_en": "A cardio exercise focusing on the muscles.",
    "description_ar": "تمرين cardio يركز على muscles.",
    "category": "CARDIO",
    "primary_muscle": "CARDIO",
    "secondary_muscles": [],
    "equipment": [
      "BODYWEIGHT"
    ],
    "difficulty": "BEGINNER",
    "instructions_en": [
      "Step 1: Assume starting position.",
      "Step 2: Perform the movement.",
      "Step 3: Return to start."
    ],
    "instructions_ar": [
      "الخطوة ١: اتخذ وضعية البداية.",
      "الخطوة ٢: قم بأداء الحركة.",
      "الخطوة ٣: عد إلى وضعية البداية."
    ],
    "tips_en": [],
    "tips_ar": [],
    "is_time_based": false,
    "default_sets": 3,
    "default_reps": 12,
    "default_duration": null,
    "default_rest": 60,
    "tags": [
      "cardio",
      "bodyweight"
    ]
  },
  {
    "id": "",
    "name_en": "Unknown Exercise",
    "name_ar": "Unknown (AR)",
    "description_en": "A cardio exercise focusing on the muscles.",
    "description_ar": "تمرين cardio يركز على muscles.",
    "category": "CARDIO",
    "primary_muscle": "CARDIO",
    "secondary_muscles": [],
    "equipment": [
      "BODYWEIGHT"
    ],
    "difficulty": "BEGINNER",
    "instructions_en": [
      "Step 1: Assume starting position.",
      "Step 2: Perform the movement.",
      "Step 3: Return to start."
    ],
    "instructions_ar": [
      "الخطوة ١: اتخذ وضعية البداية.",
      "الخطوة ٢: قم بأداء الحركة.",
      "الخطوة ٣: عد إلى وضعية البداية."
    ],
    "tips_en": [],
    "tips_ar": [],
    "is_time_based": false,
    "default_sets": 3,
    "default_reps": 12,
    "default_duration": null,
    "default_rest": 60,
    "tags": [
      "cardio",
      "bodyweight"
    ]
  },
  {
    "id": "",
    "name_en": "Unknown Exercise",
    "name_ar": "Unknown (AR)",
    "description_en": "A cardio exercise focusing on the muscles.",
    "description_ar": "تمرين cardio يركز على muscles.",
    "category": "CARDIO",
    "primary_muscle": "CARDIO",
    "secondary_muscles": [],
    "equipment": [
      "BODYWEIGHT"
    ],
    "difficulty": "BEGINNER",
    "instructions_en": [
      "Step 1: Assume starting position.",
      "Step 2: Perform the movement.",
      "Step 3: Return to start."
    ],
    "instructions_ar": [
      "الخطوة ١: اتخذ وضعية البداية.",
      "الخطوة ٢: قم بأداء الحركة.",
      "الخطوة ٣: عد إلى وضعية البداية."
    ],
    "tips_en": [],
    "tips_ar": [],
    "is_time_based": false,
    "default_sets": 3,
    "default_reps": 12,
    "default_duration": null,
    "default_rest": 60,
    "tags": [
      "cardio",
      "bodyweight"
    ]
  },
  {
    "id": "",
    "name_en": "Unknown Exercise",
    "name_ar": "Unknown (AR)",
    "description_en": "A cardio exercise focusing on the muscles.",
    "description_ar": "تمرين cardio يركز على muscles.",
    "category": "CARDIO",
    "primary_muscle": "CARDIO",
    "secondary_muscles": [],
    "equipment": [
      "BODYWEIGHT"
    ],
    "difficulty": "BEGINNER",
    "instructions_en": [
      "Step 1: Assume starting position.",
      "Step 2: Perform the movement.",
      "Step 3: Return to start."
    ],
    "instructions_ar": [
      "الخطوة ١: اتخذ وضعية البداية.",
      "الخطوة ٢: قم بأداء الحركة.",
      "الخطوة ٣: عد إلى وضعية البداية."
    ],
    "tips_en": [],
    "tips_ar": [],
    "is_time_based": false,
    "default_sets": 3,
    "default_reps": 12,
    "default_duration": null,
    "default_rest": 60,
    "tags": [
      "cardio",
      "bodyweight"
    ]
  }
]